packet_handler.v
module packet_handler(
    /* clocks and resets */
    i_clk,
    i_rst_n,

    /* input signals */
    i_data,
    i_valid,
    i_ready,
    i_last,

    /* output signals */
    o_data,
    o_ready,
    o_valid,
    o_packetLost
);
    /* clocks and resets */
    input              i_clk;
    input              i_rst_n;
    /* input signals */
    input [31:0]       i_data;
    input              i_valid;
    input              i_ready;
    input              i_last;
    /* output signals */
    output reg [295:0] o_data;
    output reg         o_ready;
    output reg         o_valid;
    output             o_packetLost;

    /* internal signals */
    /* header format values */
    /* verilator lint_off UNUSEDSIGNAL */
    reg [15:0]  msgLength;
    reg [15:0]  streamId;
    /* verilator lint_on UNUSEDSIGNAL */
    reg [31:0]  seqNumber;
    /* using unpacked array to track seqNumber based on streamId
    using 32 bits to store seqNumber and 32 elements for each streamId */
    reg [31:0]  packetTracker [31:0];
    /* serial to paraller shift register */
    reg [295:0] shiftReg;
    /* state and next state registers for FSM */
    reg [3:0]   state;
    reg [3:0]   next_state;
    /* registers to help generate o_packLost pulse */
    reg         o_packetLostReg;
    reg         o_packetLostReg_d;

    /* one-hot encoding for FSM states*/
    localparam IDLE     = 4'b0001;
    localparam HEADER   = 4'b0010;
    localparam DATA     = 4'b0100;
    localparam DONE     = 4'b1000;

    /* FSM initialization - sequential block - state registers definition */
    always @(posedge i_clk or negedge i_rst_n) begin
        if (!i_rst_n) begin
            state <= IDLE;
        end else begin
            state <= next_state;
        end
    end

    /* FSM state logic - combinational block - next state logic */
    always @(*) begin
        case (state)
            IDLE: begin
                /* transmitter asserts i_valid, data transaction
                can be initiated since o_ready is high */
                if (i_valid) begin
                    next_state = HEADER;
                end else begin
                    next_state = IDLE;
                end
            end
            /* extra state to receive and store the next 4 bytes 
            of header */
            HEADER: begin
                /* unconditional transition to next state */
                next_state = DATA;
            end
            DATA: begin
                /* transmitter asserts i_last so its done sending data */
                if (i_last) begin
                    next_state = DONE;
                end else begin
                    next_state = DATA;
                end
            end
            DONE: begin
                /* receiver asserts i_ready, data can be sent */
                if (i_ready) begin
                    next_state = IDLE;
                end else begin
                    next_state = DONE;
                end
            end
            default: begin
                next_state = IDLE;
            end
        endcase
    end

    //FSM output logic - sequential block
    always @(posedge i_clk or negedge i_rst_n) begin
        if (!i_rst_n) begin
            o_ready <= 1'b1;
            o_valid <= 1'b0;
        end else begin
            case (state)
                IDLE: begin
                    /* FPGA is ready to receive data from transmitter */
                    o_ready <= 1'b1;
                    o_valid <= 1'b0;
                end
                HEADER: begin
                    /* FPGA is ready to receive data from transmitter */
                    o_ready <= 1'b1;
                    o_valid <= 1'b0;
                end
                DATA: begin
                    /* FPGA is ready to receive data from transmitter */
                    o_ready <= 1'b1;
                    /* transmitter has sent all data, FPGA is ready to
                    send data to receiver */
                    if (i_last) begin
                        o_valid <= 1'b1;
                    end else begin
                        o_valid <= 1'b0;
                    end
                end
                DONE: begin
                    /* receiver is ready to receive data, FPGA can go
                    back to being ready to receive data from transmitter*/
                    if (i_ready) begin
                        o_valid <= 1'b0;
                        o_ready <= 1'b1;
                    end else begin
                        o_valid <= 1'b1;
                        o_ready <= 1'b0;
                    end
                end
                default: begin
                    o_ready <= 1'b0;
                    o_valid <= 1'b0;
                end
            endcase
        end
    end

    /* serial to parallel data with shift register
    and logic to extract header information
    the indexes on i_data signal are based on the fact
    that bytes are stored in little endian for each field
     of the header*/
    always @(posedge i_clk or negedge i_rst_n) begin
        if (!i_rst_n) begin
            o_data <= 296'b0;
            msgLength <= 16'b0;
            streamId <= 16'b0;
            seqNumber <= 32'b0;
            shiftReg <= 296'b0;
        end else begin
            case (state)
                IDLE: begin
                    shiftReg <= 296'b0;
                    if (i_valid && o_ready) begin
                        /* extract first 4 bytes of header fields
                        stored in little endian */
                        msgLength <= {i_data[23:16], i_data[31:24]};
                        streamId <= {i_data[7:0], i_data[15:8]};
                    end else begin
                        msgLength <= 16'b0;
                        streamId <= 16'b0;
                    end
                end
                HEADER: begin
                    /* extract last 4 bytes of header field
                    sotred in little endian */
                    seqNumber <= {i_data[7:0], i_data[15:8], i_data[23:16], i_data[31:24]};
                end
                DATA: begin
                    /* shifting 32 bits of incoming data into register */
                    shiftReg <= {shiftReg[263:0], i_data};
                end
                DONE: begin
                    /* transimitter is done sending data
                    data can be outputed to receiver as long as
                    receiver is ready */
                    if (i_ready) begin
                        o_data <= shiftReg;
                    end else begin
                        o_data <= o_data;
                    end
                end
                default: begin
                    o_data <= 296'b0;
                    msgLength <= 16'b0;
                    streamId <= 16'b0;
                    seqNumber <= 32'b0;
                    shiftReg <= 296'b0;
                end
            endcase
        end
    end

    /* Lost packet detection logic */
    integer i;
    always @(posedge i_clk or negedge i_rst_n) begin
        if (!i_rst_n) begin
            /* initializing packetTracker to 0s */
`ifndef SYNTHESIS
            for (i = 0; i < 32; i = i + 1) begin
                packetTracker[i] <= 32'b0;
            end
`endif
            o_packetLostReg <= 1'b0;
        end else begin
            case (state)
                IDLE: begin
                    o_packetLostReg <= 1'b0;
                end
                HEADER: begin
                    /* updating internal counter for incoming streamId 
                    streamId range is 1-32 and index range is 0-31 */
                    o_packetLostReg <= 1'b0;
                    packetTracker[streamId[4:0]-1] <= packetTracker[streamId[4:0]-1]+1;
                end
                DATA: begin
                    /* comparing internal counter for incoming streamId
                    with incoming seqNumber and asserting o_packetLostReg
                    if it is not the same */
                    if (packetTracker[streamId[4:0]-1] == seqNumber) begin
                        o_packetLostReg <= 1'b0;
                    end else begin
                        o_packetLostReg <= 1'b1;
                    end
                end
                DONE: begin
                    o_packetLostReg <= 1'b0;
                end
                default: begin
`ifndef SYNTHESIS
                    for (i = 0; i < 32; i = i + 1) begin
                        packetTracker[i] <= 32'b0;
                    end
`endif
                    o_packetLostReg <= 1'b0;
                end
            endcase
        end
    end

    /* o_packetLost needs to be a pulse so an 
    edge detector is used to help generate it  */
    always @(posedge i_clk or negedge i_rst_n) begin
        if (!i_rst_n) begin
            o_packetLostReg_d <= 1'b0;
        end else begin
            o_packetLostReg_d <= o_packetLostReg;
        end
    end

    /* generation of o_packetLost pulse from regisered signals */
    assign o_packetLost = o_packetLostReg & ~o_packetLostReg_d;

endmodule

packet_handler_tb.v
module packet_handler_tb;

    reg              clk;
    reg              rst_n;
    reg      [31:0]  dataIn;
    reg              validIn;
    reg              lastIn;
    wire             readyIn;
    wire     [295:0] dataOut;
    wire             validOut;
    reg              readyOut;
    wire             packetLost;

    packet_handler UTpacket_handler (
        /* clocks and resets */
        .i_clk         (clk         ),
        .i_rst_n       (rst_n       ),

        /* input interface */
        .i_data        (dataIn      ),
        .i_valid       (validIn     ),
        .i_last        (lastIn      ),
        .o_ready       (readyIn     ),

        /* output interface */
        .o_data        (dataOut     ),
        .o_valid       (validOut    ),
        .i_ready       (readyOut    ),
        .o_packetLost  (packetLost  )
    );

    initial begin
        $dumpfile("wave.vcd");
        $dumpvars(0, packet_handler_tb);
    end

    initial begin
        $monitor("%t: dataIn=%h, validIn=%b, readyOut=%b, lastIn=%b, dataOut=%h, readyIn=%b, validOut=%b, packetLost=%b, state=%b, msgLength:%h, streamId:%h, seqNumber:%h, shiftReg:%h",
        $time, dataIn, validIn, readyOut, lastIn, dataOut, readyIn, validOut, packetLost, UTpacket_handler.state, UTpacket_handler.msgLength, UTpacket_handler.streamId, UTpacket_handler.seqNumber, UTpacket_handler.shiftReg);
    end

    
    initial begin
        clk        = 1'b0;
        rst_n      = 1'b0;
        dataIn     = 'bx;
        validIn    = 1'b0;
        readyOut   = 1'b0;
        lastIn     = 1'b0;
    end

    always
    #5 clk = ~clk;

    initial begin
        #2.5 rst_n = 1'b0;
        #10  rst_n = 1'b1;

        //idle

        #10 dataIn='d0; validIn=1'b0; lastIn=1'b0; readyOut=1'b0;
        #10 dataIn='d0; validIn=1'b0; lastIn=1'b0; readyOut=1'b0;

        //sending data with valid seqNumber for streamId 15
        //sending msgLength (24) and streamId (15) in little endian
        #10 dataIn=32'h1800_0F00; validIn=1'b1; lastIn=1'b0; readyOut=1'b0;
        //sending seqNumber(1) in little endian
        #10 dataIn=32'h0100_0000; validIn=1'b1; lastIn=1'b0; readyOut=1'b0;
        //sending data 1512223444
        #10 dataIn=32'h5A22B2D4; validIn=1'b1; lastIn=1'b0; readyOut=1'b0;
        //sending data 1512223902
        #10 dataIn=32'h5A22B49E; validIn=1'b1; lastIn=1'b0; readyOut=1'b0;
        //sending data 1122223902
        #10 dataIn=32'h42E3C71E; validIn=1'b1; lastIn=1'b0; readyOut=1'b0;
        //sending data 1134123902
        #10 dataIn=32'h43995B7E; validIn=1'b1; lastIn=1'b1; readyOut=1'b0;
        //completing transaction
        #10 dataIn=32'h43995B7E; validIn=1'b0; lastIn=1'b0; readyOut=1'b0;
        //sending to receiver
        #10 dataIn=32'h43995B7E; validIn=1'b0; lastIn=1'b0; readyOut=1'b1;

        //back to idle
        #10 dataIn=32'h43995B7E; validIn=1'b0; lastIn=1'b0; readyOut=1'b0;

        //sending data with correct seqNumber for streamId 15
        //sending msgLength (24) and streamId (15) in little endian
        #10 dataIn=32'h1800_0F00; validIn=1'b1; lastIn=1'b0; readyOut=1'b0;
        //sending seqNumber(2) in little endian
        #10 dataIn=32'h0200_0000; validIn=1'b1; lastIn=1'b0; readyOut=1'b0;
        //sending data 1512223444
        #10 dataIn=32'h5A22B2D4; validIn=1'b1; lastIn=1'b0; readyOut=1'b0;
        //sending data 1512223902
        #10 dataIn=32'h5A22B49E; validIn=1'b1; lastIn=1'b0; readyOut=1'b0;
        //sending data 1122223902
        #10 dataIn=32'h42E3C71E; validIn=1'b1; lastIn=1'b0; readyOut=1'b0;
        //sending data 1134123902
        #10 dataIn=32'h43995B7E; validIn=1'b1; lastIn=1'b1; readyOut=1'b0;
        //completing transaction
        #10 dataIn=32'h43995B7E; validIn=1'b0; lastIn=1'b0; readyOut=1'b0;
        //sending to receiver
        #10 dataIn=32'h43995B7E; validIn=1'b0; lastIn=1'b0; readyOut=1'b1;

        //back to idle
        #10 dataIn=32'h43995B7E; validIn=1'b0; lastIn=1'b0; readyOut=1'b0;

        //sending data with wrong seqNumber for streamId 15 to generate o_packetLost
        //sending msgLength (24) and streamId (15) in little endian
        #10 dataIn=32'h1800_0F00; validIn=1'b1; lastIn=1'b0; readyOut=1'b0;
        //sending seqNumber(4) in little endian
        #10 dataIn=32'h0400_0000; validIn=1'b1; lastIn=1'b0; readyOut=1'b0;
        //sending data 1512223444
        #10 dataIn=32'h5A22B2D4; validIn=1'b1; lastIn=1'b0; readyOut=1'b0;
        //sending data 1512223902
        #10 dataIn=32'h5A22B49E; validIn=1'b1; lastIn=1'b0; readyOut=1'b0;
        //sending data 1122223902
        #10 dataIn=32'h42E3C71E; validIn=1'b1; lastIn=1'b0; readyOut=1'b0;
        //sending data 1134123902
        #10 dataIn=32'h43995B7E; validIn=1'b1; lastIn=1'b1; readyOut=1'b0;
        //completing transaction
        #10 dataIn=32'h43995B7E; validIn=1'b0; lastIn=1'b0; readyOut=1'b0;
        //sending to receiver
        #10 dataIn=32'h43995B7E; validIn=1'b0; lastIn=1'b0; readyOut=1'b1;

        //back to idle
        #10 dataIn=32'h43995B7E; validIn=1'b0; lastIn=1'b0; readyOut=1'b0;

        #10 rst_n   = 1'b1;
        $finish;
    end

endmodule

wave.vcd
$date
	Sun Feb  8 22:21:24 2026
$end
$version
	Icarus Verilog
$end
$timescale
	1s
$end
$scope module packet_handler_tb $end
$var wire 1 ! validOut $end
$var wire 1 " readyIn $end
$var wire 1 # packetLost $end
$var wire 296 $ dataOut [295:0] $end
$var reg 1 % clk $end
$var reg 32 & dataIn [31:0] $end
$var reg 1 ' lastIn $end
$var reg 1 ( readyOut $end
$var reg 1 ) rst_n $end
$var reg 1 * validIn $end
$scope module UTpacket_handler $end
$var wire 1 % i_clk $end
$var wire 32 + i_data [31:0] $end
$var wire 1 ' i_last $end
$var wire 1 ( i_ready $end
$var wire 1 ) i_rst_n $end
$var wire 1 * i_valid $end
$var wire 1 # o_packetLost $end
$var parameter 4 , DATA $end
$var parameter 4 - DONE $end
$var parameter 4 . HEADER $end
$var parameter 4 / IDLE $end
$var reg 16 0 msgLength [15:0] $end
$var reg 4 1 next_state [3:0] $end
$var reg 296 2 o_data [295:0] $end
$var reg 1 3 o_packetLostReg $end
$var reg 1 4 o_packetLostReg_d $end
$var reg 1 " o_ready $end
$var reg 1 ! o_valid $end
$var reg 32 5 seqNumber [31:0] $end
$var reg 296 6 shiftReg [295:0] $end
$var reg 4 7 state [3:0] $end
$var reg 16 8 streamId [15:0] $end
$var integer 32 9 i [31:0] $end
$upscope $end
$upscope $end
$enddefinitions $end
$comment Show the parameter values. $end
$dumpall
b1 /
b10 .
b1000 -
b100 ,
$end
#0
$dumpvars
b100000 9
b0 8
b1 7
b0 6
b0 5
04
x3
b0 2
b1 1
b0 0
bx +
0*
0)
0(
0'
bx &
0%
b0 $
x#
1"
0!
$end
#5
b100000 9
1%
#10
0%
#13
1)
#15
0#
03
x4
1%
#20
0%
#23
b0 &
b0 +
#25
04
1%
#30
0%
#35
1%
#40
0%
#43
b10 1
1*
b11000000000000000111100000000 &
b11000000000000000111100000000 +
#45
b100 1
b1111 8
b11000 0
b10 7
1%
#50
0%
#53
b1000000000000000000000000 &
b1000000000000000000000000 +
#55
b100 7
b1 5
1%
#60
0%
#63
b1011010001000101011001011010100 &
b1011010001000101011001011010100 +
#65
b1011010001000101011001011010100 6
1%
#70
0%
#73
b1011010001000101011010010011110 &
b1011010001000101011010010011110 +
#75
b101101000100010101100101101010001011010001000101011010010011110 6
1%
#80
0%
#83
b1000010111000111100011100011110 &
b1000010111000111100011100011110 +
#85
b10110100010001010110010110101000101101000100010101101001001111001000010111000111100011100011110 6
1%
#90
0%
#93
b1000 1
1'
b1000011100110010101101101111110 &
b1000011100110010101101101111110 +
#95
b1000 7
1!
b1011010001000101011001011010100010110100010001010110100100111100100001011100011110001110001111001000011100110010101101101111110 6
1%
#100
0%
#103
0'
0*
#105
0"
1%
#110
0%
#113
b1 1
1(
#115
b1 7
1"
0!
b1011010001000101011001011010100010110100010001010110100100111100100001011100011110001110001111001000011100110010101101101111110 $
b1011010001000101011001011010100010110100010001010110100100111100100001011100011110001110001111001000011100110010101101101111110 2
1%
#120
0%
#123
0(
#125
b0 8
b0 0
b0 6
1%
#130
0%
#133
b10 1
1*
b11000000000000000111100000000 &
b11000000000000000111100000000 +
#135
b100 1
b10 7
b1111 8
b11000 0
1%
#140
0%
#143
b10000000000000000000000000 &
b10000000000000000000000000 +
#145
b10 5
b100 7
1%
#150
0%
#153
b1011010001000101011001011010100 &
b1011010001000101011001011010100 +
#155
b1011010001000101011001011010100 6
1%
#160
0%
#163
b1011010001000101011010010011110 &
b1011010001000101011010010011110 +
#165
b101101000100010101100101101010001011010001000101011010010011110 6
1%
#170
0%
#173
b1000010111000111100011100011110 &
b1000010111000111100011100011110 +
#175
b10110100010001010110010110101000101101000100010101101001001111001000010111000111100011100011110 6
1%
#180
0%
#183
b1000 1
1'
b1000011100110010101101101111110 &
b1000011100110010101101101111110 +
#185
b1011010001000101011001011010100010110100010001010110100100111100100001011100011110001110001111001000011100110010101101101111110 6
1!
b1000 7
1%
#190
0%
#193
0'
0*
#195
0"
1%
#200
0%
#203
b1 1
1(
#205
1"
0!
b1 7
1%
#210
0%
#213
0(
#215
b0 8
b0 0
b0 6
1%
#220
0%
#223
b10 1
1*
b11000000000000000111100000000 &
b11000000000000000111100000000 +
#225
b100 1
b1111 8
b11000 0
b10 7
1%
#230
0%
#233
b100000000000000000000000000 &
b100000000000000000000000000 +
#235
b100 7
b100 5
1%
#240
0%
#243
b1011010001000101011001011010100 &
b1011010001000101011001011010100 +
#245
1#
13
b1011010001000101011001011010100 6
1%
#250
0%
#253
b1011010001000101011010010011110 &
b1011010001000101011010010011110 +
#255
0#
b101101000100010101100101101010001011010001000101011010010011110 6
14
1%
#260
0%
#263
b1000010111000111100011100011110 &
b1000010111000111100011100011110 +
#265
b10110100010001010110010110101000101101000100010101101001001111001000010111000111100011100011110 6
1%
#270
0%
#273
b1000 1
1'
b1000011100110010101101101111110 &
b1000011100110010101101101111110 +
#275
b1000 7
1!
b1011010001000101011001011010100010110100010001010110100100111100100001011100011110001110001111001000011100110010101101101111110 6
1%
#280
0%
#283
0'
0*
#285
03
0"
1%
#290
0%
#293
b1 1
1(
#295
b1 7
1"
0!
04
1%
#300
0%
#303
0(
#305
b0 8
b0 0
b0 6
1%
